tad_dftd3/__init__.py
tad_dftd3/__version__.py
tad_dftd3/defaults.py
tad_dftd3/disp.py
tad_dftd3/exception.py
tad_dftd3/py.typed
tad_dftd3/reference-c6.pt
tad_dftd3/reference.py
tad_dftd3/damping/__init__.py
tad_dftd3/damping/atm.py
tad_dftd3/damping/rational.py
tad_dftd3/data/__init__.py
tad_dftd3/data/r4r2.py
tad_dftd3/model/__init__.py
tad_dftd3/model/c6.py
tad_dftd3/model/weights.py
tad_dftd3/ncoord/__init__.py
tad_dftd3/typing/__init__.py
tad_dftd3/typing/d3.py
tad_dftd3/typing/pytorch.py
tad_dftd3-0.5.0.dist-info/licenses/LICENSE
tad_dftd3-0.5.0.dist-info/METADATA
tad_dftd3-0.5.0.dist-info/WHEEL
tad_dftd3-0.5.0.dist-info/top_level.txt
tad_dftd3-0.5.0.dist-info/RECORD
