Metadata-Version: 2.4
Name: tad_dftd3
Version: 0.5.0
Summary: Torch autodiff DFT-D3 implementation
Author: "Sebastian Ehlert, Marvin Friede"
License: Apache-2.0
Project-URL: Documentation, https://tad-dftd3.readthedocs.io/en/latest/
Project-URL: Source Code, https://github.com/dftd3/tad-dftd3
Project-URL: Tracker, https://github.com/dftd3/tad-dftd3/issues
Classifier: Intended Audience :: Developers
Classifier: Intended Audience :: Science/Research
Classifier: Natural Language :: English
Classifier: Operating System :: MacOS
Classifier: Operating System :: Microsoft :: Windows
Classifier: Operating System :: POSIX
Classifier: Operating System :: POSIX :: Linux
Classifier: Programming Language :: Python :: 3
Classifier: Programming Language :: Python :: 3 :: Only
Classifier: Programming Language :: Python :: 3.8
Classifier: Programming Language :: Python :: 3.9
Classifier: Programming Language :: Python :: 3.10
Classifier: Programming Language :: Python :: 3.11
Classifier: Programming Language :: Python :: 3.12
Classifier: Programming Language :: Python :: Implementation :: CPython
Classifier: Topic :: Scientific/Engineering :: Chemistry
Classifier: Typing :: Typed
Requires-Python: <3.13,>=3.8
License-File: LICENSE
Requires-Dist: numpy<2
Requires-Dist: tad-mctc==0.5.3
Requires-Dist: torch<3,>=1.11
Provides-Extra: dev
Requires-Dist: black; extra == "dev"
Requires-Dist: covdefaults; extra == "dev"
Requires-Dist: mypy; extra == "dev"
Requires-Dist: pre-commit; extra == "dev"
Requires-Dist: pylint; extra == "dev"
Requires-Dist: pytest; extra == "dev"
Requires-Dist: pytest-cov; extra == "dev"
Requires-Dist: pytest-random-order; extra == "dev"
Requires-Dist: pytest-xdist; extra == "dev"
Requires-Dist: tox; extra == "dev"
Provides-Extra: tox
Requires-Dist: covdefaults; extra == "tox"
Requires-Dist: pytest; extra == "tox"
Requires-Dist: pytest-cov; extra == "tox"
Requires-Dist: pytest-random-order; extra == "tox"
Requires-Dist: pytest-xdist; extra == "tox"
Dynamic: license-file
